LICENSE
README.md
setup.cfg
setup.py
serp_bot/__init__.py
serp_bot.egg-info/PKG-INFO
serp_bot.egg-info/SOURCES.txt
serp_bot.egg-info/dependency_links.txt
serp_bot.egg-info/requires.txt
serp_bot.egg-info/top_level.txt
serp_bot.egg-info/zip-safe
serp_bot/aol/__init__.py
serp_bot/bing/__init__.py
serp_bot/ddg/__init__.py
serp_bot/excite/__init__.py
serp_bot/google/__init__.py
serp_bot/lycos/__init__.py
serp_bot/yahoo/__init__.py
serp_bot/yandex/__init__.py