Metadata-Version: 2.1
Name: serp-bot
Version: 0.1.0
Summary: Search Engine Results Page Bot
Home-page: https://github.com/supratikchatterjee16/serp_bot
Author: Supratik Chatterjee
Author-email: supratikdevm96@gmail.com
License: UNKNOWN
Keywords: serp,bot,webscraping,scraping,search engine,package,python,crawler
Platform: UNKNOWN
Classifier: Programming Language :: Python :: 3
Classifier: Operating System :: OS Independent
License-File: LICENSE
